db1_test_package/__init__.py
db1_test_package/test.py
db1_test_package-0.2.0.dist-info/LICENSE
db1_test_package-0.2.0.dist-info/METADATA
db1_test_package-0.2.0.dist-info/WHEEL
db1_test_package-0.2.0.dist-info/top_level.txt
db1_test_package-0.2.0.dist-info/RECORD
