Metadata-Version: 2.1
Name: db1-test-package
Version: 0.2.0
Home-page: https://github.com/db1-io/db1-py
Author: 
Author-email: 
Project-URL: Source Code, https://github.com/db1-io/db1-py
Classifier: Programming Language :: Python :: 3
Classifier: License :: OSI Approved :: MIT License
Classifier: Operating System :: POSIX :: Linux
Requires-Python: >=3.7
License-File: LICENSE
Requires-Dist: numpy
Requires-Dist: pyarrow
Requires-Dist: pandas
Requires-Dist: protobuf (>=4.21.11)
Requires-Dist: requests
Requires-Dist: websocket-client
